aicodeprep/__init__.py
aicodeprep/default_config.yaml
aicodeprep/main.py
aicodeprep-0.2.2.dist-info/LICENSE
aicodeprep-0.2.2.dist-info/METADATA
aicodeprep-0.2.2.dist-info/WHEEL
aicodeprep-0.2.2.dist-info/entry_points.txt
aicodeprep-0.2.2.dist-info/top_level.txt
aicodeprep-0.2.2.dist-info/RECORD
