Metadata-Version: 2.1
Name: aicodeprep
Version: 0.2.2
Summary: Prepare code for AI chatbot assistance
Author-email: Tom Brothers <wuu73@yahoo.com>
License: MIT License
Project-URL: Homepage, https://github.com/detroittommy879/aicodeprep
Keywords: ai,code,preparation,chatbot
Classifier: License :: OSI Approved :: MIT License
Classifier: Programming Language :: Python
Classifier: Programming Language :: Python :: 3
Requires-Python: >=3.6
License-File: LICENSE
Requires-Dist: pyperclip
Requires-Dist: pyyaml
